gms_cli/__init__.py
gms_cli/database.py
gms_cli/main.py
gms_cli/utils.py
gms_cli-3.0.0.dist-info/entry_points.txt
gms_cli-3.0.0.dist-info/METADATA
gms_cli-3.0.0.dist-info/WHEEL
gms_cli-3.0.0.dist-info/RECORD
