Metadata-Version: 2.1
Name: gms-cli
Version: 3.0.0
Summary: cli-gms is a command-line gym management system (GMS) application. It provides a user-friendly interface for managing members, their plans, packages, and payments. The application also allows you to view member details, payment history, and plan details. The CLI application is built using Python and leverages the Click library for command-line interface functionality. It stores data in a MySQL database and uses the Rich library for enhanced user interface experience.
License: MIT
Author: Libin Lalu
Author-email: libinlalu000@gmail.com
Requires-Python: >=3.9.5,<4.0.0
Classifier: License :: OSI Approved :: MIT License
Classifier: Programming Language :: Python :: 3
Classifier: Programming Language :: Python :: 3.10
Classifier: Programming Language :: Python :: 3.11
Classifier: Programming Language :: Python :: 3.12
Requires-Dist: click (>=8.1.7,<9.0.0)
Requires-Dist: keyring (>=25.5.0,<26.0.0)
Requires-Dist: mysql-connector-python (>=9.1.0,<10.0.0)
Requires-Dist: python-dateutil (>=2.9.0.post0,<3.0.0)
Requires-Dist: questionary (>=2.0.1,<3.0.0)
Requires-Dist: rich (>=13.9.4,<14.0.0)
